materialdash/__init__.py
materialdash/admin/__init__.py
materialdash/admin/apps.py
materialdash/admin/options.py
materialdash/admin/settings.py
materialdash/admin/sites.py
materialdash/admin/urls.py
materialdash/admin/views.py
materialdash/admin/widgets.py
materialdash/apps.py
materialdash/locale/es/LC_MESSAGES/django.mo
materialdash/locale/es/LC_MESSAGES/django.po
materialdash/locale/es_AR/LC_MESSAGES/django.mo
materialdash/locale/es_AR/LC_MESSAGES/django.po
materialdash/locale/ru/LC_MESSAGES/django.mo
materialdash/locale/ru/LC_MESSAGES/django.po
materialdash/locale/uk/LC_MESSAGES/django.mo
materialdash/locale/uk/LC_MESSAGES/django.po
materialdash/locale/zh_Hans/LC_MESSAGES/django.mo
materialdash/locale/zh_Hans/LC_MESSAGES/django.po
materialdash/static/admin/js/SelectFilter2.js
materialdash/static/admin/js/inlines.js
materialdash/static/admin/js/inlines.min.js
materialdash/static/admin/js/prepopulate.js
materialdash/static/materialdash/admin/css/additional_submit_line.min.css
materialdash/static/materialdash/admin/css/admin-out-black.min.css
materialdash/static/materialdash/admin/css/admin-out-green.min.css
materialdash/static/materialdash/admin/css/admin-out-night.min.css
materialdash/static/materialdash/admin/css/admin-out-red.min.css
materialdash/static/materialdash/admin/css/admin-out.min.css
materialdash/static/materialdash/admin/css/app_content.min.css
materialdash/static/materialdash/admin/css/autocomplete.min.css
materialdash/static/materialdash/admin/css/base_site-black.min.css
materialdash/static/materialdash/admin/css/base_site-green.min.css
materialdash/static/materialdash/admin/css/base_site-night.min.css
materialdash/static/materialdash/admin/css/base_site-red.min.css
materialdash/static/materialdash/admin/css/base_site-responsive.min.css
materialdash/static/materialdash/admin/css/base_site-theme.min.css
materialdash/static/materialdash/admin/css/base_site.min.css
materialdash/static/materialdash/admin/css/change_form.min.css
materialdash-0.0.24.3.dist-info/METADATA
materialdash-0.0.24.3.dist-info/WHEEL
materialdash-0.0.24.3.dist-info/licenses/LICENCE.TXT
materialdash-0.0.24.3.dist-info/RECORD
