Metadata-Version: 2.4
Name: materialdash
Version: 0.0.24.3
Summary: MaterialDash é uma interface de administração moderna para Django, baseada em Material Design.
License-File: LICENCE.TXT
Author: Anderson Freitas
Author-email: freitas.dev@proton.me
Requires-Python: >=3.10,<4.0
Classifier: Programming Language :: Python :: 3
Classifier: Programming Language :: Python :: 3.10
Classifier: Programming Language :: Python :: 3.11
Classifier: Programming Language :: Python :: 3.12
Classifier: Programming Language :: Python :: 3.13
Classifier: Programming Language :: Python :: 3.14
